<?xml version="1.0" encoding="UTF-8" ?>
<!DOCTYPE mapper PUBLIC "-//mybatis.org//DTD Mapper 3.0//EN" "http://mybatis.org/dtd/mybatis-3-mapper.dtd">
<mapper namespace="com.pethub.mapper.PostMapper">

    <select id="selectPage" resultType="com.pethub.pojo.vo.PostVO">
        select
            p.id,
            p.cover_url as coverUrl,
            p.title,
            p.content,
            u.username,
            p.like_count as likeCount,
            p.comment_count as commentCount,
            case when pl.id is null then false else true end as liked,
            p.status,
            p.create_time as createTime
        from post p
        left join user u on p.user_id = u.id
        left join post_like pl on pl.post_id = p.id and pl.user_id = #{currentUserId}
        <where>
            p.is_deleted = 0
            <if test="title != null and title != ''">
                and p.title like concat('%', #{title}, '%')
            </if>
            <if test="username != null and username != ''">
                and u.username like concat('%', #{username}, '%')
            </if>
            <if test="status != null">
                and p.status = #{status}
            </if>
        </where>
        order by p.create_time desc
    </select>

    <select id="selectPageByUserId" resultType="com.pethub.pojo.vo.PostVO">
        select
            p.id,
            p.cover_url as coverUrl,
            p.title,
            p.content,
            u.username,
            p.like_count as likeCount,
            p.comment_count as commentCount,
            case when pl.id is null then false else true end as liked,
            p.status,
            p.create_time as createTime
        from post p
        left join user u on p.user_id = u.id
        left join post_like pl on pl.post_id = p.id and pl.user_id = #{userId}
        where p.user_id = #{userId}
          and p.is_deleted = 0
        order by p.create_time desc
    </select>

    <select id="selectDetailById" resultType="com.pethub.pojo.vo.PostDetailVO">
        select
            p.id,
            p.cover_url as coverUrl,
            p.title,
            p.content,
            u.username,
            p.like_count as likeCount,
            p.comment_count as commentCount,
            case when pl.id is null then false else true end as liked,
            p.status,
            p.reject_reason as rejectReason,
            p.create_time as createTime
        from post p
        left join user u on p.user_id = u.id
        left join post_like pl on pl.post_id = p.id and pl.user_id = #{currentUserId}
        where p.id = #{id}
          and p.is_deleted = 0
        limit 1
    </select>

    <select id="selectEntityById" resultType="com.pethub.pojo.entity.Post">
        select
            id,
            user_id as userId,
            cover_url as coverUrl,
            title,
            content,
            like_count as likeCount,
            comment_count as commentCount,
            status,
            reject_reason as rejectReason,
            create_time as createTime,
            update_time as updateTime,
            is_deleted as isDeleted
        from post
        where id = #{id}
          and is_deleted = 0
        limit 1
    </select>

    <select id="selectEntityByIdAndUserId" resultType="com.pethub.pojo.entity.Post">
        select
            id,
            user_id as userId,
            cover_url as coverUrl,
            title,
            content,
            like_count as likeCount,
            comment_count as commentCount,
            status,
            reject_reason as rejectReason,
            create_time as createTime,
            update_time as updateTime,
            is_deleted as isDeleted
        from post
        where id = #{id}
          and user_id = #{userId}
          and is_deleted = 0
        limit 1
    </select>

    <insert id="insert" useGeneratedKeys="true" keyProperty="post.id">
        insert into post (
            user_id,
            cover_url,
            title,
            content,
            like_count,
            comment_count,
            status,
            reject_reason
        ) values (
            #{userId},
            #{post.coverUrl},
            #{post.title},
            #{post.content},
            0,
            0,
            0,
            null
        )
    </insert>

    <update id="updateByIdAndUserId">
        update post
        set cover_url = #{post.coverUrl},
            title = #{post.title},
            content = #{post.content},
            status = 0,
            reject_reason = null
        where id = #{id}
          and user_id = #{userId}
          and is_deleted = 0
    </update>

    <update id="updateLikeCount">
        update post
        set like_count = #{likeCount}
        where id = #{id}
          and is_deleted = 0
    </update>

    <update id="updateCommentCount">
        update post
        set comment_count = #{commentCount}
        where id = #{id}
          and is_deleted = 0
    </update>

    <update id="updateStatusById">
        update post
        set status = #{status},
            reject_reason = #{rejectReason}
        where id = #{id}
          and is_deleted = 0
    </update>

    <update id="deleteById">
        update post
        set is_deleted = 1
        where id = #{id}
          and is_deleted = 0
    </update>

    <update id="deleteByIdAndUserId">
        update post
        set is_deleted = 1
        where id = #{id}
          and user_id = #{userId}
          and is_deleted = 0
    </update>

</mapper>
